unibot_hn/Misc.py
unibot_hn/PID.py
unibot_hn/__init__.py
unibot_hn/board.py
unibot_hn/camera.py
unibot_hn/img_processing.py
unibot_hn/robot_config.py
unibot_hn/robot_param_init.txt
unibot_hn/setObjectColor.py
unibot_hn/setScreenObjectColor.py
unibot_hn/unibot.py
unibot_hn-0.1.4.dist-info/LICENSE
unibot_hn-0.1.4.dist-info/METADATA
unibot_hn-0.1.4.dist-info/WHEEL
unibot_hn-0.1.4.dist-info/RECORD
